{
  "version": "0.3.14-fixed",
  "steps": [
    {
      "tag": "CreateField",
      "model": "User",
      "field": "firstName",
      "type": "String",
      "arity": "Optional"
    },
    {
      "tag": "CreateField",
      "model": "User",
      "field": "lastName",
      "type": "String",
      "arity": "Optional"
    },
    {
      "tag": "CreateField",
      "model": "User",
      "field": "Customers",
      "type": "Customers",
      "arity": "List"
    },
    {
      "tag": "DeleteField",
      "model": "User",
      "field": "name"
    },
    {
      "tag": "CreateField",
      "model": "Customers",
      "field": "userId",
      "type": "Int",
      "arity": "Required"
    },
    {
      "tag": "CreateField",
      "model": "Customers",
      "field": "user",
      "type": "User",
      "arity": "Required"
    },
    {
      "tag": "CreateDirective",
      "location": {
        "path": {
          "tag": "Field",
          "model": "Customers",
          "field": "user"
        },
        "directive": "relation"
      }
    },
    {
      "tag": "CreateArgument",
      "location": {
        "tag": "Directive",
        "path": {
          "tag": "Field",
          "model": "Customers",
          "field": "user"
        },
        "directive": "relation"
      },
      "argument": "fields",
      "value": "[userId]"
    },
    {
      "tag": "CreateArgument",
      "location": {
        "tag": "Directive",
        "path": {
          "tag": "Field",
          "model": "Customers",
          "field": "user"
        },
        "directive": "relation"
      },
      "argument": "references",
      "value": "[id]"
    },
    {
      "tag": "CreateField",
      "model": "Categories",
      "field": "platform",
      "type": "Platform",
      "arity": "Optional"
    },
    {
      "tag": "CreateDirective",
      "location": {
        "path": {
          "tag": "Field",
          "model": "Categories",
          "field": "platform"
        },
        "directive": "relation"
      }
    },
    {
      "tag": "CreateArgument",
      "location": {
        "tag": "Directive",
        "path": {
          "tag": "Field",
          "model": "Categories",
          "field": "platform"
        },
        "directive": "relation"
      },
      "argument": "fields",
      "value": "[platformId]"
    },
    {
      "tag": "CreateArgument",
      "location": {
        "tag": "Directive",
        "path": {
          "tag": "Field",
          "model": "Categories",
          "field": "platform"
        },
        "directive": "relation"
      },
      "argument": "references",
      "value": "[id]"
    },
    {
      "tag": "DeleteField",
      "model": "Categories",
      "field": "Platform"
    }
  ]
}